.cargo/config.toml
.sqlx/query-1975ecaf2913207959a4951af399535d3c8846a3cfa39f7d16724a9bd81f0f0e.json
.sqlx/query-1c442e92b9ee5966e2ec8365efea3f51ce176accde3170a1478b809e65a480bc.json
.sqlx/query-1e73eafe2dcbc67bd0af0c670b9cbd33178e524c97ad4e693293443bb3b79c68.json
.sqlx/query-492a2ff55d1cce8f660539e2669f8752b0046b0a4bb25c9989ceacc329486fcc.json
.sqlx/query-4e38a23703a343a33e2146baa1039cd3669b91c39adc562c315b6207d3893e1c.json
.sqlx/query-4e78abd6be2ac9c0beed34a950021899348b664eebeda80ad5cf1cd33466d786.json
.sqlx/query-517ba464982dbb0568a648e49c9d0f8736955599e16b1c1b75430877dbd73c65.json
.sqlx/query-53da30c2ccfd1ad50e7eaa1d4404e2e58a88880f79fea07b01e5ff36360eb01c.json
.sqlx/query-5a747ceb50106db9507e3af0da7cf8b066f8e83ff02df83595af2260e95baa95.json
.sqlx/query-659d060b324bef8da0bbd4224540c90cb60ac01dbf9d5d4399665ac63c70c979.json
.sqlx/query-90411315922c30d4169332969f97264cbb00b48b4694b249b874095b0b43c024.json
.sqlx/query-a4d2aa2e85389d921b4c1581321838689d73b9496a26b3116bafd0584e500016.json
.sqlx/query-a7ee55d391857381df97974b2a6f5abf9726c5e4a674bd8035bd49c2b22de181.json
.sqlx/query-aba97737d0a90f98bc608f419687f97f62ed3f827144033c6b3cdf19b158cad6.json
.sqlx/query-abb1324b349c40b2830e7ebcc703244461e39a260d50991f2ce9479fd80c1440.json
.sqlx/query-ad24e2220da11b3db9b82ca14d289d47c23eb464fd3c64396a0d1479aa6d9b1b.json
.sqlx/query-bd5104b86e1a04f3b2c0616905af9f72ce35a68cace9cbf9134cfc580e51d9cf.json
.sqlx/query-def27e03861b63955f0807d5e1d4c62084f591ed8df9bfc6f1d6fffe9a8ba728.json
.sqlx/query-f55789b64e7bba86213f6eea4cfc33f1b8a11d58b6ec4eba246af184d8053ca6.json
.sqlx/query-f8899dd12ce459ee73b9247fc1575ac06d8e415bc09e930f060608bd89f59d49.json
tensorzero/__init__.py
tensorzero/client.py
tensorzero/generated_types.py
tensorzero/internal.py
tensorzero/omit_type.py
tensorzero/py.typed
tensorzero/tensorzero.abi3.so
tensorzero/tensorzero.pyi
tensorzero/types.py
tensorzero/util.py
tensorzero-2026.1.8.dist-info/METADATA
tensorzero-2026.1.8.dist-info/WHEEL
tensorzero-2026.1.8.dist-info/RECORD
