Metadata-Version: 2.4
Name: tensorzero
Version: 2026.1.8
Classifier: Development Status :: 5 - Production/Stable
Classifier: Intended Audience :: Developers
Classifier: License :: OSI Approved :: Apache Software License
Classifier: Topic :: Scientific/Engineering :: Artificial Intelligence
Classifier: Typing :: Typed
Requires-Dist: dacite>=1.9.2
Requires-Dist: httpx>=0.27.0
Requires-Dist: typing-extensions>=4.12.2
Requires-Dist: uuid-utils>=0.9.0
Summary: The Python client for TensorZero
Keywords: artificial intelligence,ai,machine learning,ml,large language model,large language models,llm,llms,natural language processing,NLP,generative ai,genai
Author-email: Viraj Mehta <viraj@tensorzero.com>, Gabriel Bianconi <gabriel@tensorzero.com>, Aaron Hill <aaron@tensorzero.com>
License-Expression: Apache-2.0
Requires-Python: >=3.10
Project-URL: Documentation, https://tensorzero.com/docs/
Project-URL: Homepage, https://tensorzero.com/
Project-URL: Issues, https://github.com/tensorzero/tensorzero/issues
Project-URL: ReleaseNotes, https://github.com/tensorzero/tensorzero/releases
Project-URL: Repository, https://github.com/tensorzero/tensorzero
